cceyes/__init__.py
cceyes/_version.py
cceyes/config.py
cceyes/main.py
cceyes/models.py
cceyes/productions.py
cceyes/providers.py
examples/__init__.py
examples/etl/__init__.py
examples/etl/betaseries/__init__.py
examples/etl/betaseries/shows.py
examples/etl/betaseries/utils.py
examples/etl/google/__init__.py
examples/etl/google/books.py
examples/etl/steam/__init__.py
examples/etl/steam/games.py
examples/etl/tmdb/__init__.py
examples/etl/tmdb/movies.py
cceyes-0.2.6.dist-info/METADATA
cceyes-0.2.6.dist-info/WHEEL
cceyes-0.2.6.dist-info/entry_points.txt
cceyes-0.2.6.dist-info/top_level.txt
cceyes-0.2.6.dist-info/RECORD
