Metadata-Version: 2.1
Name: cceyes
Version: 0.2.6
Requires-Python: >=3.6, <4
Requires-Dist: requests
Requires-Dist: typer
Requires-Dist: PyYAML
Requires-Dist: pydantic
